read_counts/__init__.py
read_counts/maths.py
read_counts-0.2.0.dist-info/LICENSE
read_counts-0.2.0.dist-info/METADATA
read_counts-0.2.0.dist-info/WHEEL
read_counts-0.2.0.dist-info/top_level.txt
read_counts-0.2.0.dist-info/RECORD
