Metadata-Version: 2.1
Name: read-counts
Version: 0.2.0
Summary: Example of how to package Python code for release
Home-page: https://github.com/prithikasritharan/read-counts
Author: Prithika Sritharan
Author-email: prithika.sritharan@quadram.ac.uk
License: MIT
Platform: UNKNOWN
Requires-Python: >=3.7
License-File: LICENSE
Requires-Dist: numpy
Requires-Dist: pandas
Provides-Extra: dev
Requires-Dist: bump2version ; extra == 'dev'
Requires-Dist: pytest ; extra == 'dev'
Requires-Dist: black ; extra == 'dev'
Requires-Dist: mypy ; extra == 'dev'
Requires-Dist: flake8 ; extra == 'dev'
